[
    {
        "results": {
            "ATE_true": -7044.780790238633,
            "ATE_IPTW": -9126.214539035233,
            "RMSE_IPTW": 2081.4337487965995,
            "ATE_AIPW": -9127.020819537527,
            "RMSE_AIPW": 2082.240029298894
        },
        "config": {
            "training": {
                "num_epochs": 10,
                "batch_size": 128,
                "learning_rate": 0.001,
                "weight_decay": 0.01,
                "project_tag": "lalonde_cps"
            },
            "model": {
                "num_layers": 4,
                "dropout_rate": 0.1,
                "embedding_dim": 512,
                "num_heads": 16
            }
        }
    }
]